{
  "beers-top": [
    { "name": "3 Schténg",
      "type": "Fermentation haute",
      "degres": "6%",
      "location": "Grain d'Orge"
    },
    {
        "name": "La Chouffe Blonde",
        "type": "Fermentation haute",
        "degres": "8%",
        "location": "Brasserie d'Achouffe"
    },
    {
        "name": "Coq Hardi",
        "type": "Fermentation basse, Blonde",
        "degres": "5,5 %",
        "location": "Brasserie Haacht"
    },
    {
        "name": "Corsendonk Blonde",
        "type": "Fermentation haute",
        "degres": "6,5 %",
        "location": "Brasserie du Bocq pour la Brasserie Corsendonk"
    }
  ],
  "beers-reste": [
      {
        "name": "Cuvée des Trolls",
        "type": "Fermentation haute, Blonde",
        "degres": "7 %",
        "location": "Brasserie Dubuisson"
      },
      {
        "name": "De Koninck",
        "type": "Ambrée",
        "degres": "5,2 %",
        "location": "Brasserie De Koninck (Brasserie Duvel Moortgat)"
      },
      {
        "name": "Duvel",
        "type": "Fermentation haute",
        "degres": "8,5 %",
        "location": "Brasserie Duvel Moortgat"
      },
      {
        "name": "Durboyse blonde",
        "type": "Blonde",
        "degres": "6,5 %",
        "location": "Brasserie Lefèbvre"
      },
      {
        "name": "Duvel Tripel Hop",
        "type": "Fermentation haute",
        "degres": "9,5 %",
        "location": "Brasserie Duvel Moortgat"
      },
      {
        "name": "Fantôme",
        "type": "Fermentation haute",
        "degres": "8 %",
        "location": "Brasserie Fantôme"
      },
      {
        "name": "La Forgeronne",
        "type": "Ambrée",
        "degres": "6 %",
        "location": "Brasserie de Tubize"
      },
      {
        "name": "Grimbergen Blond  Abbaye",
        "type": "Fermentation haute",
        "degres": "6,7 %",
        "location": "Alken-Maes (Heineken)"
      },
      {
        "name": "Grimbergen Goud",
        "type": "Fermentation haute, Blonde",
        "degres": "8 %",
        "location": "Alken-Maes (Heineken)"
      },
      {
        "name": "Hoegaarden",
        "type": "Fermentation haute, Blanche",
        "degres": "4,9 %",
        "location": "Brasserie De Kluis (InBev)"
      },
      {
        "name": "Jupiler",
        "type": "Pils",
        "degres": "5,2 %",
        "location": "Brasserie Jupiler (AB InBev)"
      },
      {
        "name": "Cristal 1928",
        "type": "Fermentation basse, Pils",
        "degres": "5,8 %",
        "location": "Alken-Maes (Heineken)"
      },
      {
        "name": "Cuvée du Flo",
        "type": "Ambrée Fermentation haute, Ambrée",
        "degres": "8,5 %",
        "location": "Brasserie du Flo"
      },
      {
        "name": "DeuS",
        "type": "Brut, Blonde",
        "degres": "11,5 %",
        "location": "Brasserie Bosteels"
      },
      {
        "name": "Vedett Extra Blond",
        "type": "Blonde",
        "degres": "5,2 %",
        "location": "Brasserie Duvel Moortgat"
      },
      {
        "name": "Watou Tripel",
        "type": "Triple",
        "degres": "7,5 %",
        "location": "Brasserie St. Bernardus"
      },
      {
        "name": "Zulte",
        "type": "ermentation haute, Brune",
        "degres": "4,7 %",
        "location": "Alken-Maes (Heineken)"
      },
      {
        "name": "Westmalle Tripel",
        "type": "Trappiste",
        "degres": "9,5 %",
        "location": "Abbaye Notre-Dame du Sacré-Cœur de Westmalle"
      }
  ]
}
